{
  "scriptCompleted": true,
  "filesAnalyzed": 20,
  "filesSkipped": [],
  "results": [
    {
      "path": "supabase/rollbacks/20260601000000_001_schema_down.sql",
      "language": "sql",
      "fileCategory": "data",
      "totalLines": 23,
      "nonEmptyLines": 21,
      "metrics": {
        "importCount": 0,
        "exportCount": 0,
        "functionCount": 0,
        "classCount": 0,
        "definitionCount": 0
      }
    },
    {
      "path": "supabase/rollbacks/20260601000100_002_functions_down.sql",
      "language": "sql",
      "fileCategory": "data",
      "totalLines": 21,
      "nonEmptyLines": 20,
      "metrics": {
        "importCount": 0,
        "exportCount": 0,
        "functionCount": 0,
        "classCount": 0,
        "definitionCount": 0
      }
    },
    {
      "path": "supabase/rollbacks/20260601000300_004_views_and_rpcs_down.sql",
      "language": "sql",
      "fileCategory": "data",
      "totalLines": 8,
      "nonEmptyLines": 8,
      "metrics": {
        "importCount": 0,
        "exportCount": 0,
        "functionCount": 0,
        "classCount": 0,
        "definitionCount": 0
      }
    },
    {
      "path": "supabase/rollbacks/20260601002700_admin_event_lifetime_editing_down.sql",
      "language": "sql",
      "fileCategory": "data",
      "totalLines": 14,
      "nonEmptyLines": 12,
      "metrics": {
        "importCount": 0,
        "exportCount": 0,
        "functionCount": 0,
        "classCount": 0,
        "definitionCount": 0
      }
    },
    {
      "path": "supabase/rollbacks/20260601017000_event_status_enum_and_validate_checks_down.sql",
      "language": "sql",
      "fileCategory": "data",
      "totalLines": 939,
      "nonEmptyLines": 872,
      "definitions": [
        {
          "name": "public",
          "kind": "view",
          "fields": [],
          "startLine": 48,
          "endLine": 48
        },
        {
          "name": "events_local_date_published_idx",
          "kind": "index",
          "fields": [],
          "startLine": 37,
          "endLine": 37
        },
        {
          "name": "events_published_city_start_datetime_idx",
          "kind": "index",
          "fields": [],
          "startLine": 39,
          "endLine": 39
        },
        {
          "name": "events_published_feed_idx",
          "kind": "index",
          "fields": [],
          "startLine": 41,
          "endLine": 41
        },
        {
          "name": "events_published_local_date_city_idx",
          "kind": "index",
          "fields": [],
          "startLine": 43,
          "endLine": 43
        },
        {
          "name": "events_published_start_id_idx",
          "kind": "index",
          "fields": [],
          "startLine": 45,
          "endLine": 45
        }
      ],
      "metrics": {
        "importCount": 0,
        "exportCount": 0,
        "functionCount": 0,
        "classCount": 0,
        "definitionCount": 6
      }
    },
    {
      "path": "supabase/rollbacks/20260601018000_fix_events_enriched_enum_cast_down.sql",
      "language": "sql",
      "fileCategory": "data",
      "totalLines": 15,
      "nonEmptyLines": 12,
      "metrics": {
        "importCount": 0,
        "exportCount": 0,
        "functionCount": 0,
        "classCount": 0,
        "definitionCount": 0
      }
    },
    {
      "path": "supabase/rollbacks/20260601019000_restore_events_enriched_cursor_signature_down.sql",
      "language": "sql",
      "fileCategory": "data",
      "totalLines": 89,
      "nonEmptyLines": 85,
      "metrics": {
        "importCount": 0,
        "exportCount": 0,
        "functionCount": 0,
        "classCount": 0,
        "definitionCount": 0
      }
    },
    {
      "path": "supabase/rollbacks/20260601020000_event_embeddings_and_similarity_down.sql",
      "language": "sql",
      "fileCategory": "data",
      "totalLines": 82,
      "nonEmptyLines": 70,
      "metrics": {
        "importCount": 0,
        "exportCount": 0,
        "functionCount": 0,
        "classCount": 0,
        "definitionCount": 0
      }
    },
    {
      "path": "supabase/rollbacks/20260601021000_admin_event_decisions_down.sql",
      "language": "sql",
      "fileCategory": "data",
      "totalLines": 258,
      "nonEmptyLines": 232,
      "metrics": {
        "importCount": 0,
        "exportCount": 0,
        "functionCount": 0,
        "classCount": 0,
        "definitionCount": 0
      }
    },
    {
      "path": "supabase/rollbacks/20260601022000_source_auto_reject_and_stats_down.sql",
      "language": "sql",
      "fileCategory": "data",
      "totalLines": 14,
      "nonEmptyLines": 11,
      "metrics": {
        "importCount": 0,
        "exportCount": 0,
        "functionCount": 0,
        "classCount": 0,
        "definitionCount": 0
      }
    },
    {
      "path": "supabase/rollbacks/20260601023000_fix_ai_settings_rpc_grants_down.sql",
      "language": "sql",
      "fileCategory": "data",
      "totalLines": 18,
      "nonEmptyLines": 14,
      "metrics": {
        "importCount": 0,
        "exportCount": 0,
        "functionCount": 0,
        "classCount": 0,
        "definitionCount": 0
      }
    },
    {
      "path": "supabase/rollbacks/20260601024000_admin_retry_dead_tag_queue_down.sql",
      "language": "sql",
      "fileCategory": "data",
      "totalLines": 17,
      "nonEmptyLines": 14,
      "metrics": {
        "importCount": 0,
        "exportCount": 0,
        "functionCount": 0,
        "classCount": 0,
        "definitionCount": 0
      }
    },
    {
      "path": "supabase/rollbacks/20260601025000_baton_rouge_sources_down.sql",
      "language": "sql",
      "fileCategory": "data",
      "totalLines": 69,
      "nonEmptyLines": 63,
      "metrics": {
        "importCount": 0,
        "exportCount": 0,
        "functionCount": 0,
        "classCount": 0,
        "definitionCount": 0
      }
    },
    {
      "path": "supabase/rollbacks/20260601026000_fix_unindexed_fk_admin_event_decisions_down.sql",
      "language": "sql",
      "fileCategory": "data",
      "totalLines": 10,
      "nonEmptyLines": 7,
      "metrics": {
        "importCount": 0,
        "exportCount": 0,
        "functionCount": 0,
        "classCount": 0,
        "definitionCount": 0
      }
    },
    {
      "path": "supabase/rollbacks/20260601027000_user_notification_preferences_down.sql",
      "language": "sql",
      "fileCategory": "data",
      "totalLines": 37,
      "nonEmptyLines": 29,
      "metrics": {
        "importCount": 0,
        "exportCount": 0,
        "functionCount": 0,
        "classCount": 0,
        "definitionCount": 0
      }
    },
    {
      "path": "supabase/rollbacks/20260601028000_search_events_radius_filter_down.sql",
      "language": "sql",
      "fileCategory": "data",
      "totalLines": 117,
      "nonEmptyLines": 112,
      "metrics": {
        "importCount": 0,
        "exportCount": 0,
        "functionCount": 0,
        "classCount": 0,
        "definitionCount": 0
      }
    },
    {
      "path": "supabase/rollbacks/20260601029000_find_similar_events_by_id_down.sql",
      "language": "sql",
      "fileCategory": "data",
      "totalLines": 22,
      "nonEmptyLines": 16,
      "metrics": {
        "importCount": 0,
        "exportCount": 0,
        "functionCount": 0,
        "classCount": 0,
        "definitionCount": 0
      }
    },
    {
      "path": "supabase/rollbacks/20260601030000_push_and_notifications_down.sql",
      "language": "sql",
      "fileCategory": "data",
      "totalLines": 51,
      "nonEmptyLines": 42,
      "metrics": {
        "importCount": 0,
        "exportCount": 0,
        "functionCount": 0,
        "classCount": 0,
        "definitionCount": 0
      }
    },
    {
      "path": "supabase/rollbacks/20260601031000_event_change_notifications_down.sql",
      "language": "sql",
      "fileCategory": "data",
      "totalLines": 29,
      "nonEmptyLines": 23,
      "metrics": {
        "importCount": 0,
        "exportCount": 0,
        "functionCount": 0,
        "classCount": 0,
        "definitionCount": 0
      }
    },
    {
      "path": "supabase/rollbacks/20260601032000_drop_old_search_events_overload_down.sql",
      "language": "sql",
      "fileCategory": "data",
      "totalLines": 121,
      "nonEmptyLines": 114,
      "metrics": {
        "importCount": 0,
        "exportCount": 0,
        "functionCount": 0,
        "classCount": 0,
        "definitionCount": 0
      }
    }
  ]
}