{"nodes": [{"id": "workflows_ci", "label": "CI Workflow", "file_type": "document", "source_file": ".github/workflows/ci.yml", "source_location": null, "source_url": null, "captured_at": null, "author": null, "contributor": null}, {"id": "concept_secret_scan", "label": "Secret Scanning (TruffleHog + Gitleaks)", "file_type": "concept", "source_file": ".github/workflows/ci.yml", "source_location": "lines 22-40", "source_url": null, "captured_at": null, "author": null, "contributor": null}, {"id": "concept_type_drift_check", "label": "DB Type Drift Check", "file_type": "concept", "source_file": ".github/workflows/ci.yml", "source_location": "lines 79-114", "source_url": null, "captured_at": null, "author": null, "contributor": null}, {"id": "concept_database_types_ts", "label": "database.types.ts Generated Contract", "file_type": "concept", "source_file": ".github/workflows/ci.yml", "source_location": "line 103", "source_url": null, "captured_at": null, "author": null, "contributor": null}], "edges": [{"source": "workflows_ci", "target": "concept_secret_scan", "relation": "references", "confidence": "EXTRACTED", "confidence_score": 1.0, "source_file": ".github/workflows/ci.yml", "source_location": "lines 22-40", "weight": 1.0}, {"source": "workflows_ci", "target": "concept_type_drift_check", "relation": "references", "confidence": "EXTRACTED", "confidence_score": 1.0, "source_file": ".github/workflows/ci.yml", "source_location": "lines 79-114", "weight": 1.0}, {"source": "concept_type_drift_check", "target": "concept_database_types_ts", "relation": "references", "confidence": "EXTRACTED", "confidence_score": 1.0, "source_file": ".github/workflows/ci.yml", "source_location": "line 103", "weight": 1.0}, {"source": "concept_database_types_ts", "target": "concept_contracts_package", "relation": "shares_data_with", "confidence": "EXTRACTED", "confidence_score": 1.0, "source_file": ".github/workflows/ci.yml", "source_location": "line 103", "weight": 1.0}], "hyperedges": []}